tsnex/__init__.py
tsnex/tsne.py
tsnex/tsne_test.py
tsnex-0.0.3.dist-info/LICENSE
tsnex-0.0.3.dist-info/METADATA
tsnex-0.0.3.dist-info/WHEEL
tsnex-0.0.3.dist-info/top_level.txt
tsnex-0.0.3.dist-info/RECORD
