Metadata-Version: 2.2
Name: tsnex
Version: 0.0.3
Summary: Minimal t-distributed stochastic neighbor embedding (t-SNE) implementation in JAX.
Author-email: Albert Alonso <alonfnt@pm.me>
License: MIT License
Project-URL: Homepage, https://github.com/alonfnt/tsnex
Project-URL: Documentation, https://github.com/alonfnt/tsnex
Project-URL: Source, https://github.com/alonfnt/tsnex
Project-URL: Bug Tracker, https://github.com/alonfnt/tsnex/issues
Keywords: jax,tsne,python,data-visualization
Classifier: Development Status :: 3 - Alpha
Classifier: Intended Audience :: Developers
Classifier: License :: OSI Approved :: MIT License
Classifier: Programming Language :: Python :: 3
Requires-Python: >=3.10
License-File: LICENSE
Requires-Dist: jax
Requires-Dist: pcax
